livezip/__init__.py
livezip/__main__.py
livezip/encode.py
livezip/models.py
livezip/storage.py
livezip/stream.py
livezip-0.1.0.dist-info/LICENSE
livezip-0.1.0.dist-info/WHEEL
livezip-0.1.0.dist-info/METADATA
livezip-0.1.0.dist-info/RECORD
